LICENSE
benchling_api_client/benchling_client.py
benchling_api_client/client.py
benchling_api_client/extensions.py
benchling_api_client/py.typed
benchling_api_client/types.py
benchling_api_client-2.0.60.dist-info/LICENSE
benchling_api_client-2.0.60.dist-info/WHEEL
benchling_api_client-2.0.60.dist-info/METADATA
benchling_api_client-2.0.60.dist-info/RECORD
